resizeImgForML/__init__.py
resizeImgForML/resizeImgForML.py
resizeImgForML-0.0.7.dist-info/LICENSE
resizeImgForML-0.0.7.dist-info/METADATA
resizeImgForML-0.0.7.dist-info/WHEEL
resizeImgForML-0.0.7.dist-info/top_level.txt
resizeImgForML-0.0.7.dist-info/RECORD
