Metadata-Version: 2.1
Name: resizeImgForML
Version: 0.0.7
Summary: `resizeImgForML` is a package for resize images for machie learning.
Home-page: https://github.com/k-mawa/resizeImgForML
Author: Kosuke Mawatari
Author-email: UNKNOWN
License: MIT
Keywords: machine,machine learning,resize,Pillow,PIL,openCV
Platform: UNKNOWN
Classifier: Programming Language :: Python :: 3
Classifier: Programming Language :: Python :: 3.6
Classifier: License :: OSI Approved :: MIT License
Requires-Dist: Pillow (==8.0.1)
